MANIFEST.in
README.txt
setup.cfg
setup.py
Products/__init__.py
Products/__init__.pyc
Products.mediaLink.egg-info/PKG-INFO
Products.mediaLink.egg-info/SOURCES.txt
Products.mediaLink.egg-info/dependency_links.txt
Products.mediaLink.egg-info/entry_points.txt
Products.mediaLink.egg-info/namespace_packages.txt
Products.mediaLink.egg-info/not-zip-safe
Products.mediaLink.egg-info/paster_plugins.txt
Products.mediaLink.egg-info/requires.txt
Products.mediaLink.egg-info/top_level.txt
Products/mediaLink/README.txt
Products/mediaLink/__init__.py
Products/mediaLink/__init__.pyc
Products/mediaLink/config.py
Products/mediaLink/config.pyc
Products/mediaLink/configure.zcml
Products/mediaLink/browser/__init__.py
Products/mediaLink/browser/__init__.pyc
Products/mediaLink/browser/configure.zcml
Products/mediaLink/content/__init__.py
Products/mediaLink/content/__init__.pyc
Products/mediaLink/content/configure.zcml
Products/mediaLink/content/medialink.py
Products/mediaLink/content/medialink.pyc
Products/mediaLink/interfaces/__init__.py
Products/mediaLink/interfaces/__init__.pyc
Products/mediaLink/interfaces/medialink.py
Products/mediaLink/interfaces/medialink.pyc
Products/mediaLink/portlets/__init__.py
Products/mediaLink/portlets/__init__.pyc
Products/mediaLink/portlets/configure.zcml
Products/mediaLink/profiles/default/factorytool.xml
Products/mediaLink/profiles/default/metadata.xml
Products/mediaLink/profiles/default/portlets.xml
Products/mediaLink/profiles/default/rolemap.xml
Products/mediaLink/profiles/default/types.xml
Products/mediaLink/profiles/default/types/MediaLink.xml
Products/mediaLink/tests/__init__.py
Products/mediaLink/tests/base.py
Products/mediaLink/tests/test_doctest.py
docs/CONTRIBUTORS.txt
docs/HISTORY.txt
docs/INSTALL.txt
docs/LICENSE.GPL
docs/LICENSE.txt