Metadata-Version: 1.1
Name: Products.mediaLink
Version: 0.0.1
Summary: Folderish Link
Home-page: https://github.com/intk/Products.mediaLink
Author: David Jonas, Andre Goncalves
Author-email: david@itsnotthatkind.org, andre@intk.com
License: GPL
Download-URL: https://github.com/intk/Products.mediaLink/tarball/0.5
Keywords: plone type link folderish
Platform: UNKNOWN
Classifier: Framework :: Plone
Classifier: Intended Audience :: Developers
Classifier: License :: OSI Approved :: GNU General Public License (GPL)
